spectral_cube/__init__.py
spectral_cube/_moments.py
spectral_cube/analysis_utilities.py
spectral_cube/base_class.py
spectral_cube/conftest.py
spectral_cube/cube_utils.py
spectral_cube/dask_spectral_cube.py
spectral_cube/lower_dimensional_structures.py
spectral_cube/masks.py
spectral_cube/np_compat.py
spectral_cube/spectral_axis.py
spectral_cube/spectral_cube.py
spectral_cube/stokes_spectral_cube.py
spectral_cube/utils.py
spectral_cube/version.py
spectral_cube/visualization-tools.py
spectral_cube/wcs_utils.py
spectral_cube/ytcube.py
spectral_cube/io/__init__.py
spectral_cube/io/casa_image.py
spectral_cube/io/casa_masks.py
spectral_cube/io/class_lmv.py
spectral_cube/io/core.py
spectral_cube/io/fits.py
spectral_cube/tests/__init__.py
spectral_cube/tests/helpers.py
spectral_cube/tests/setup_package.py
spectral_cube/tests/test_analysis_functions.py
spectral_cube/tests/test_casafuncs.py
spectral_cube/tests/test_cube_utils.py
spectral_cube/tests/test_dask.py
spectral_cube/tests/test_io.py
spectral_cube/tests/test_masks.py
spectral_cube/tests/test_moments.py
spectral_cube/tests/test_performance.py
spectral_cube/tests/test_projection.py
spectral_cube/tests/test_regrid.py
spectral_cube/tests/test_spectral_axis.py
spectral_cube/tests/test_spectral_cube.py
spectral_cube/tests/test_stokes_spectral_cube.py
spectral_cube/tests/test_subcubes.py
spectral_cube/tests/test_visualization.py
spectral_cube/tests/test_wcs_utils.py
spectral_cube/tests/utilities.py
spectral_cube/tests/data/255-fk5.reg
spectral_cube/tests/data/255-pixel.reg
spectral_cube/tests/data/Makefile
spectral_cube/tests/data/__init__.py
spectral_cube/tests/data/cubewcs1.hdr
spectral_cube/tests/data/cubewcs2.hdr
spectral_cube/tests/data/example_cube.fits
spectral_cube/tests/data/example_cube.lmv
spectral_cube/tests/data/fk5.reg
spectral_cube/tests/data/fk5_twoboxes.reg
spectral_cube/tests/data/greisen2006.hdr
spectral_cube/tests/data/header_jybeam.hdr
spectral_cube/tests/data/image.reg
spectral_cube-0.6.7.dist-info/licenses/LICENSE.rst
spectral_cube-0.6.7.dist-info/METADATA
spectral_cube-0.6.7.dist-info/WHEEL
spectral_cube-0.6.7.dist-info/top_level.txt
spectral_cube-0.6.7.dist-info/RECORD
